CMakeLists.txt
LICENSE
MANIFEST.in
README.md
pyproject.toml
setup.py
AmberMDrun/CMakeLists.txt
AmberMDrun/__init__.py
AmberMDrun/equil.py
AmberMDrun/main.cpp
AmberMDrun/main.py
AmberMDrun/mmpbsa.py
AmberMDrun/pyamber.cpp
AmberMDrun/pyamber.py
AmberMDrun/version.py
AmberMDrun.egg-info/PKG-INFO
AmberMDrun.egg-info/SOURCES.txt
AmberMDrun.egg-info/dependency_links.txt
AmberMDrun.egg-info/entry_points.txt
AmberMDrun.egg-info/not-zip-safe
AmberMDrun.egg-info/requires.txt
AmberMDrun.egg-info/top_level.txt
AmberMDrun/extern/pybind11/.appveyor.yml
AmberMDrun/extern/pybind11/.clang-format
AmberMDrun/extern/pybind11/.clang-tidy
AmberMDrun/extern/pybind11/.cmake-format.yaml
AmberMDrun/extern/pybind11/.codespell-ignore-lines
AmberMDrun/extern/pybind11/.git
AmberMDrun/extern/pybind11/.gitattributes
AmberMDrun/extern/pybind11/.gitignore
AmberMDrun/extern/pybind11/.pre-commit-config.yaml
AmberMDrun/extern/pybind11/.readthedocs.yml
AmberMDrun/extern/pybind11/CMakeLists.txt
AmberMDrun/extern/pybind11/LICENSE
AmberMDrun/extern/pybind11/MANIFEST.in
AmberMDrun/extern/pybind11/README.rst
AmberMDrun/extern/pybind11/noxfile.py
AmberMDrun/extern/pybind11/pyproject.toml
AmberMDrun/extern/pybind11/setup.cfg
AmberMDrun/extern/pybind11/setup.py
AmberMDrun/extern/pybind11/.github/CODEOWNERS
AmberMDrun/extern/pybind11/.github/CONTRIBUTING.md
AmberMDrun/extern/pybind11/.github/dependabot.yml
AmberMDrun/extern/pybind11/.github/labeler.yml
AmberMDrun/extern/pybind11/.github/labeler_merged.yml
AmberMDrun/extern/pybind11/.github/pull_request_template.md
AmberMDrun/extern/pybind11/.github/ISSUE_TEMPLATE/bug-report.yml
AmberMDrun/extern/pybind11/.github/ISSUE_TEMPLATE/config.yml
AmberMDrun/extern/pybind11/.github/matchers/pylint.json
AmberMDrun/extern/pybind11/.github/workflows/ci.yml
AmberMDrun/extern/pybind11/.github/workflows/configure.yml
AmberMDrun/extern/pybind11/.github/workflows/format.yml
AmberMDrun/extern/pybind11/.github/workflows/labeler.yml
AmberMDrun/extern/pybind11/.github/workflows/pip.yml
AmberMDrun/extern/pybind11/.github/workflows/upstream.yml
AmberMDrun/extern/pybind11/docs/Doxyfile
AmberMDrun/extern/pybind11/docs/Makefile
AmberMDrun/extern/pybind11/docs/basics.rst
AmberMDrun/extern/pybind11/docs/benchmark.py
